setup.py
RajatinoPackage/Binomialdistribution.py
RajatinoPackage/Gaussiandistribution.py
RajatinoPackage/Generaldistribution.py
RajatinoPackage/__init__.py
RajatinoPackage.egg-info/PKG-INFO
RajatinoPackage.egg-info/SOURCES.txt
RajatinoPackage.egg-info/dependency_links.txt
RajatinoPackage.egg-info/not-zip-safe
RajatinoPackage.egg-info/top_level.txt