Metadata-Version: 1.0
Name: RajatinoPackage
Version: 0.1
Summary: Gaussian distributions
Home-page: UNKNOWN
Author: Rajat Baxi
Author-email: UNKNOWN
License: UNKNOWN
Platform: UNKNOWN
